Workbook

Sheet Instructions
A1: PQC Migration Evaluation Framework — How to Use
A3: SHEETS
A4: Scoring | B4: Main input sheet. Enter 1 (met) or 0 (not met) for each criterion per nation. Sub-factor and category scores calculate automatically in the grey and coloured rows.
A5: Evidence | B5: Companion to Scoring. Paste source URL, document name, and access date next to each criterion.
A6: Results | B6: Auto-calculated dashboard. Shows final weighted scores (0–100), sub-factor breakdown, and a radar chart comparing all nations.
A8: HOW TO SCORE
A9: 1 | B9: Open the Scoring sheet. Edit the nation names in row 5 (columns C–F).
A10: 2 | B10: Work through each criterion. Enter 1 if you have clear evidence the criterion is met, 0 if evidence shows it is not met, or leave blank if evidence is insufficient.
A11: 3 | B11: Grey rows auto-calculate the sub-factor score (ticks ÷ total criteria, 0.00–1.00). Coloured rows auto-calculate the category score (average of sub-factor scores).
A12: 4 | B12: The Results sheet updates instantly. Final score = weighted sum × 100.
A14: WEIGHTS
A15: Cat 1 | B15: Cryptographic Agility & Migration Readiness — 20%
A16: Cat 2 | B16: Governance & Coordination — 25%
A17: Cat 3 | B17: Risk & Technical Feasibility — 20%
A18: Cat 4 | B18: Standardisation & Compatibility — 15%
A19: Cat 5 | B19: Technical — 20%
A21: ADDING NATIONS
A22: Note | B22: The sheet supports 4 nations (columns C–F). To add a 5th, insert a column to the right of F, copy formulas and conditional formatting from column F, and also update the Results sheet formulas accordingly.

Sheet Scoring
A1: PQC Migration Evaluation Framework — Scoring Sheet
A2: 1 = criteria met | 0 = criteria not met | scores auto-calculate in red rows
A4: Sub-factor | B4: Criterion | C4: Nation 1 | D4: Nation 2 | E4: Nation 3 | F4: Nation 4
B5: Nation names → | C5: Nation 1 | D5: Nation 2 | E5: Nation 3 | F5: Nation 4
A7: Category 1 · Cryptographic Agility & Migration Readiness (20%) — How adaptable are systems to cryptographic change?
A8: 1.1 Inventory & Asset Awareness | B8: ← 5 criteria
B9: National effort to identify and map cryptographic assets has been mandated
B10: Inventory scope extends to critical infrastructure
B11: Tooling in use or under development for asset discovery
B12: Inventory is maintained on an ongoing basis
B13: Governmental support for asset discovery through public funding, research programmes, or national initiatives
A14: 1.1 score | B14: (sum ÷ 5) | C14: =SUM(C9:C13)/(COUNT(C9:C13)+COUNTBLANK(C9:C13)) -> 0 | D14: =SUM(D9:D13)/(COUNT(D9:D13)+COUNTBLANK(D9:D13)) -> 0 | E14: =SUM(E9:E13)/(COUNT(E9:E13)+COUNTBLANK(E9:E13)) -> 0 | F14: =SUM(F9:F13)/(COUNT(F9:F13)+COUNTBLANK(F9:F13)) -> 0
A15: 1.2 Migration Agility | B15: ← 2 criteria
B16: Modular cryptographic implementations that allow algorithm replacement exist
B17: Testing environments for PQC transition have been established
B18: Documented migration procedures exist for at least one critical sector
A19: 1.2 score | B19: (sum ÷ 2) | C19: =SUM(C16:C18)/(COUNT(C16:C18)+COUNTBLANK(C16:C18)) -> 0 | D19: =SUM(D16:D17)/(COUNT(D16:D17)+COUNTBLANK(D16:D17)) -> 0 | E19: =SUM(E16:E17)/(COUNT(E16:E17)+COUNTBLANK(E16:E17)) -> 0 | F19: =SUM(F16:F17)/(COUNT(F16:F17)+COUNTBLANK(F16:F17)) -> 0
A20: 1.3 Operational Integration | B20: ← 3 criteria
B21: PQC readiness requirements are contained in standard development processes
B22: Security review processes include a cryptographic agility assessment step
B23: Vendor or supplier agreements reference cryptographic agility requirements
A24: 1.3 score | B24: (sum ÷ 3) | C24: =SUM(C21:C23)/(COUNT(C21:C23)+COUNTBLANK(C21:C23)) -> 0 | D24: =SUM(D21:D23)/(COUNT(D21:D23)+COUNTBLANK(D21:D23)) -> 0 | E24: =SUM(E21:E23)/(COUNT(E21:E23)+COUNTBLANK(E21:E23)) -> 0 | F24: =SUM(F21:F23)/(COUNT(F21:F23)+COUNTBLANK(F21:F23)) -> 0
A25: 1.4 Hybrid Migration Support | B25: ← 3 criteria
B26: Hybrid classical/PQC mechanisms are being developed or deployed
B27: National policy endorses hybrid approaches for transitioning
B28: PQC and QKD hybrid integration is being actively researched or piloted
A29: 1.4 score | B29: (sum ÷ 3) | C29: =SUM(C26:C28)/(COUNT(C26:C28)+COUNTBLANK(C26:C28)) -> 0 | D29: =SUM(D26:D28)/(COUNT(D26:D28)+COUNTBLANK(D26:D28)) -> 0 | E29: =SUM(E26:E28)/(COUNT(E26:E28)+COUNTBLANK(E26:E28)) -> 0 | F29: =SUM(F26:F28)/(COUNT(F26:F28)+COUNTBLANK(F26:F28)) -> 0
A30: 1.5 Supply Chain & Vendor Readiness | B30: ← 3 criteria
B31: Major domestic vendors have committed to or ship PQC-capable products
B32: Government procurement requirements include PQC readiness criteria
B33: PQC-capable products are commercially available from domestic suppliers
A34: 1.5 score | B34: (sum ÷ 3) | C34: =SUM(C31:C33)/(COUNT(C31:C33)+COUNTBLANK(C31:C33)) -> 0 | D34: =SUM(D31:D33)/(COUNT(D31:D33)+COUNTBLANK(D31:D33)) -> 0 | E34: =SUM(E31:E33)/(COUNT(E31:E33)+COUNTBLANK(E31:E33)) -> 0 | F34: =SUM(F31:F33)/(COUNT(F31:F33)+COUNTBLANK(F31:F33)) -> 0
A35: Category 1 Score (weight 20%) | C35: =AVERAGE(C14,C19,C24,C29,C34) -> 0 | D35: =AVERAGE(D14,D19,D24,D29,D34) -> 0 | E35: =AVERAGE(E14,E19,E24,E29,E34) -> 0 | F35: =AVERAGE(F14,F19,F24,F29,F34) -> 0
A37: Category 2 · Governance & Coordination (25%) — How is the transition organised and managed?
A38: 2.1 National Strategy | B38: ← 3 criteria
B39: Formal PQC strategy or master plan document has been published
B40: Strategy includes a timeline and clear milestones
B41: Strategy is backed through governmental funding
A42: 2.1 score | B42: (sum ÷ 3) | C42: =SUM(C39:C41)/(COUNT(C39:C41)+COUNTBLANK(C39:C41)) -> 0 | D42: =SUM(D39:D41)/(COUNT(D39:D41)+COUNTBLANK(D39:D41)) -> 0 | E42: =SUM(E39:E41)/(COUNT(E39:E41)+COUNTBLANK(E39:E41)) -> 0 | F42: =SUM(F39:F41)/(COUNT(F39:F41)+COUNTBLANK(F39:F41)) -> 0
A43: 2.2 Coordination | B43: ← 4 criteria
B44: Dedicated national PQC working group exists
B45: A public-private coordination mechanism is formally established
B46: Critical infrastructure operators are formally included in national coordination
B47: Coordination extends to academic and research institutions
A48: 2.2 score | B48: (sum ÷ 4) | C48: =SUM(C44:C47)/(COUNT(C44:C47)+COUNTBLANK(C44:C47)) -> 0 | D48: =SUM(D44:D47)/(COUNT(D44:D47)+COUNTBLANK(D44:D47)) -> 0 | E48: =SUM(E44:E47)/(COUNT(E44:E47)+COUNTBLANK(E44:E47)) -> 0 | F48: =SUM(F44:F47)/(COUNT(F44:F47)+COUNTBLANK(F44:F47)) -> 0
A49: 2.3 Regulation | B49: ← 3 criteria
B50: Legal or regulatory framework mandates PQC adoption in at least one sector
B51: Compliance deadlines have been published
B52: Guidance documents have been published for regulated entities
A53: 2.3 score | B53: (sum ÷ 3) | C53: =SUM(C50:C52)/(COUNT(C50:C52)+COUNTBLANK(C50:C52)) -> 0 | D53: =SUM(D50:D52)/(COUNT(D50:D52)+COUNTBLANK(D50:D52)) -> 0 | E53: =SUM(E50:E52)/(COUNT(E50:E52)+COUNTBLANK(E50:E52)) -> 0 | F53: =SUM(F50:F52)/(COUNT(F50:F52)+COUNTBLANK(F50:F52)) -> 0
A54: 2.4 Workforce | B54: ← 3 criteria
B55: Government-funded training for PQC is active
B56: National strategy contains a workforce or education component
B57: Active academic research programmes in PQC exist
A58: 2.4 score | B58: (sum ÷ 3) | C58: =SUM(C55:C57)/(COUNT(C55:C57)+COUNTBLANK(C55:C57)) -> 0 | D58: =SUM(D55:D57)/(COUNT(D55:D57)+COUNTBLANK(D55:D57)) -> 0 | E58: =SUM(E55:E57)/(COUNT(E55:E57)+COUNTBLANK(E55:E57)) -> 0 | F58: =SUM(F55:F57)/(COUNT(F55:F57)+COUNTBLANK(F55:F57)) -> 0
A59: 2.5 International Cooperation | B59: ← 3 criteria
B60: Actively participates in international PQC standardisation (ETSI, ISO, IETF, etc.)
B61: Domestic standards designed for interoperability with international standards
B62: Contributes to international PQC processes
A63: 2.5 score | B63: (sum ÷ 3) | C63: =SUM(C60:C62)/(COUNT(C60:C62)+COUNTBLANK(C60:C62)) -> 0 | D63: =SUM(D60:D62)/(COUNT(D60:D62)+COUNTBLANK(D60:D62)) -> 0 | E63: =SUM(E60:E62)/(COUNT(E60:E62)+COUNTBLANK(E60:E62)) -> 0 | F63: =SUM(F60:F62)/(COUNT(F60:F62)+COUNTBLANK(F60:F62)) -> 0
A64: Category 2 Score (weight 25%) | C64: =AVERAGE(C63,C58,C53,C48,C42) -> 0 | D64: =SUM(D63,D58,D53,D48,D42) -> 0 | E64: =SUM(E63,E58,E53,E48,E42) -> 0 | F64: =SUM(F63,F58,F53,F48,F42) -> 0
A66: Category 3 · Risk & Technical Feasibility (20%) — Can the migration realistically and securely be implemented?
A67: 3.1 Quantum Weakness | B67: ← 3 criteria
B68: National initiatives exist to identify vulnerable cryptographic systems in critical sectors
B69: High-priority sectors have been prioritised for migration
B70: Data requiring HNDL protection has been classified
A71: 3.1 score | B71: (sum ÷ 3) | C71: =SUM(C68:C70)/(COUNT(C68:C70)+COUNTBLANK(C68:C70)) -> 0 | D71: =SUM(D68:D70)/(COUNT(D68:D70)+COUNTBLANK(D68:D70)) -> 0 | E71: =SUM(E68:E70)/(COUNT(E68:E70)+COUNTBLANK(E68:E70)) -> 0 | F71: =SUM(F68:F70)/(COUNT(F68:F70)+COUNTBLANK(F68:F70)) -> 0
A72: 3.2 Expected Impact | B72: ← 2 criteria
B73: High-priority assets have individual or sectoral risk assessments
B74: Data is classified by sensitivity level and migration urgency
A75: 3.2 score | B75: (sum ÷ 2) | C75: =SUM(C73:C74)/(COUNT(C73:C74)+COUNTBLANK(C73:C74)) -> 0 | D75: =SUM(D73:D74)/(COUNT(D73:D74)+COUNTBLANK(D73:D74)) -> 0 | E75: =SUM(E73:E74)/(COUNT(E73:E74)+COUNTBLANK(E73:E74)) -> 0 | F75: =SUM(F73:F74)/(COUNT(F73:F74)+COUNTBLANK(F73:F74)) -> 0
A76: 3.3 Migration Resourcing & Planning Clarity | B76: ← 2 criteria
B77: Cost estimates for full PQC migration have been developed
B78: Public sector migration is funded through an identified budget or programme
A79: 3.3 score | B79: (sum ÷ 2) | C79: =SUM(C77:C78)/(COUNT(C77:C78)+COUNTBLANK(C77:C78)) -> 0 | D79: =SUM(D77:D78)/(COUNT(D77:D78)+COUNTBLANK(D77:D78)) -> 0 | E79: =SUM(E77:E78)/(COUNT(E77:E78)+COUNTBLANK(E77:E78)) -> 0 | F79: =SUM(F77:F78)/(COUNT(F77:F78)+COUNTBLANK(F77:F78)) -> 0
A80: 3.4 Performance & Hardware Readiness | B80: ← 2 criteria
B81: PQC performance has been benchmarked on existing hardware
B82: Lightweight PQC solutions for IoT are in development
A83: 3.4 score | B83: (sum ÷ 2) | C83: =SUM(C81:C82)/(COUNT(C81:C82)+COUNTBLANK(C81:C82)) -> 0 | D83: =SUM(D81:D82)/(COUNT(D81:D82)+COUNTBLANK(D81:D82)) -> 0 | E83: =SUM(E81:E82)/(COUNT(E81:E82)+COUNTBLANK(E81:E82)) -> 0 | F83: =SUM(F81:F82)/(COUNT(F81:F82)+COUNTBLANK(F81:F82)) -> 0
A84: Category 3 Score (weight 20%) | C84: =AVERAGE(C71,C75,C79,C83) -> 0 | D84: =SUM(D71,D75,D79,D83) -> 0 | E84: =SUM(E71,E75,E79,E83) -> 0 | F84: =SUM(F71,F75,F79,F83) -> 0
A86: Category 4 · Standardisation & Compatibility (15%) — How well does the migration align with standards and existing ecosystems?
A87: 4.1 Interoperability | B87: ← 3 criteria
B88: PQC standards are designed with international interoperability as a goal
B89: Interoperability testing has been conducted or is in progress
B90: Protocol-level integration has been addressed (TLS, DNSSEC, etc.)
A91: 4.1 score | B91: (sum ÷ 3) | C91: =SUM(C88:C90)/(COUNT(C88:C90)+COUNTBLANK(C88:C90)) -> 0 | D91: =SUM(D88:D90)/(COUNT(D88:D90)+COUNTBLANK(D88:D90)) -> 0 | E91: =SUM(E88:E90)/(COUNT(E88:E90)+COUNTBLANK(E88:E90)) -> 0 | F91: =SUM(F88:F90)/(COUNT(F88:F90)+COUNTBLANK(F88:F90)) -> 0
A92: 4.2 Standards Alignment | B92: ← 2 criteria
B93: Nation has formally adopted or mapped to NIST PQC final standards
B94: Standards documents are publicly accessible
A95: 4.2 score | B95: (sum ÷ 2) | C95: =SUM(C93:C94)/(COUNT(C93:C94)+COUNTBLANK(C93:C94)) -> 0 | D95: =SUM(D93:D94)/(COUNT(D93:D94)+COUNTBLANK(D93:D94)) -> 0 | E95: =SUM(E93:E94)/(COUNT(E93:E94)+COUNTBLANK(E93:E94)) -> 0 | F95: =SUM(F93:F94)/(COUNT(F93:F94)+COUNTBLANK(F93:F94)) -> 0
A96: 4.3 Certification & Validation Infrastructure | B96: ← 3 criteria
B97: A recognised body capable of certifying PQC implementations exists
B98: At least one PQC implementation has achieved formal certification at the nation's stated assurance level
B99: Published verification requirements specify a minimum assurance level comparable to Common Criteria EAL4 or higher
A100: 4.3 score | B100: (sum ÷ 3) | C100: =SUM(C97:C99)/(COUNT(C97:C99)+COUNTBLANK(C97:C99)) -> 0 | D100: =SUM(D97:D99)/(COUNT(D97:D99)+COUNTBLANK(D97:D99)) -> 0 | E100: =SUM(E97:E99)/(COUNT(E97:E99)+COUNTBLANK(E97:E99)) -> 0 | F100: =SUM(F97:F99)/(COUNT(F97:F99)+COUNTBLANK(F97:F99)) -> 0
A101: Category 4 Score (weight 15%) | C101: =AVERAGE(C91,C95,C100) -> 0 | D101: =SUM(D91,D95,D100) -> 0 | E101: =SUM(E91,E95,E100) -> 0 | F101: =SUM(F91,F95,F100) -> 0
A103: Category 5 · Technical (20%) — How well does the migration follow technical standards and become quantum-proof?
A104: 5.1 Algorithmic Coverage | B104: ← 3 criteria
B105: Algorithm selection covers all primary use cases (authentication, key exchange, signing)
B106: Algorithm selection reflects a documented technical rationale (security margin, performance trade-off, or domestic priority)
...

Sheet Evidence
A1: PQC Evaluation Framework — Evidence & Source Documentation
A2: Document the source or evidence for each criterion. Include document name, URL, and date accessed.
A4: Sub-factor | B4: Criterion | C4: South Korea — Evidence / Source | D4: Nation 2 — Evidence / Source | E4: Nation 3 — Evidence / Source | F4: Nation 4 — Evidence / Source
A5: Category 1 · Cryptographic Agility & Migration Readiness
A6: 1.1 Inventory & Asset Awareness
B7: National effort to identify and map cryptographic assets has been mandated
B8: Inventory scope extends to critical infrastructure
B9: Tooling in use or under development for asset discovery
B10: Inventory is maintained on an ongoing basis
B11: Governmental support for asset discovery through public funding, research programmes, or national initiatives
A12: 1.2 Migration Agility
B13: Modular cryptographic implementations that allow algorithm replacement exist
B14: Testing environments for PQC transition have been established
B15: Documented migration procedures exist for at least one critical sector
A16: 1.3 Operational Integration
B17: PQC readiness requirements are contained in standard development processes
B18: Security review processes include a cryptographic agility assessment step
B19: Vendor or supplier agreements reference cryptographic agility requirements
A20: 1.4 Hybrid Migration Support
B21: Hybrid classical/PQC mechanisms are being developed or deployed
B22: National policy endorses hybrid approaches for transitioning
B23: PQC and QKD hybrid integration is being actively researched or piloted
A24: 1.5 Supply Chain & Vendor Readiness
B25: Major domestic vendors have committed to or ship PQC-capable products
B26: Government procurement requirements include PQC readiness criteria
B27: PQC-capable products are commercially available from domestic suppliers
A29: Category 2 · Governance & Coordination
A30: 2.1 National Strategy
B31: Formal PQC strategy or master plan document has been published
B32: Strategy includes a timeline and clear milestones
B33: Strategy is backed through governmental funding
A34: 2.2 Coordination
B35: Dedicated national PQC working group exists
B36: A public-private coordination mechanism is formally established
B37: Critical infrastructure operators are formally included in national coordination
B38: Coordination extends to academic and research institutions
A39: 2.3 Regulation
B40: Legal or regulatory framework mandates PQC adoption in at least one sector
B41: Compliance deadlines have been published
B42: Guidance documents have been published for regulated entities
A43: 2.4 Workforce
B44: Government-funded training for PQC is active
B45: National strategy contains a workforce or education component
B46: Active academic research programmes in PQC exist
A47: 2.5 International Cooperation
B48: Actively participates in international PQC standardisation (ETSI, ISO, IETF, etc.)
B49: Domestic standards designed for interoperability with international standards
B50: Contributes algorithms, specifications, or expertise to international processes
A52: Category 3 · Risk & Technical Feasibility
A53: 3.1 Quantum Weakness
B54: National initiatives exist to identify vulnerable cryptographic systems in critical sectors
B55: High-priority sectors have been prioritised for migration
B56: Data requiring HNDL protection has been classified
A57: 3.2 Expected Impact
B58: High-priority assets have individual or sectoral risk assessments
B59: Data is classified by sensitivity level and migration urgency
A60: 3.3 Migration Resourcing & Planning Clarity
B61: Cost estimates for full PQC migration have been developed
B62: Public sector migration is funded through an identified budget or programme
A63: 3.4 Performance & Hardware Readiness
B64: PQC performance has been benchmarked on existing hardware
B65: Lightweight PQC solutions for IoT are in development
A67: Category 4 · Standardisation & Compatibility
A68: 4.1 Interoperability
B69: PQC standards are designed with international interoperability as a goal
B70: Interoperability testing has been conducted or is in progress
B71: Protocol-level integration has been addressed (TLS, DNSSEC, etc.)
A72: 4.2 Standards Alignment
B73: Nation's selected algorithms were produced through a formal, transparent, and multi-round standardisation or competitive evaluation process (NIST, ISO, or domestic equivalent)
B74: Standards documents are publicly accessible
A75: 4.3 Certification & Validation Infrastructure
B76: A recognised body capable of certifying PQC implementations exists
B77: At least one PQC implementation has achieved formal certification at the nation's stated assurance level
B78: Published verification requirements specify a minimum assurance level comparable to Common Criteria EAL4 or higher
A80: Category 5 · Technical
A81: 5.1 Algorithmic Coverage
B82: Algorithm selection covers all primary use cases (authentication, key exchange, signing)
B83: Algorithm selection reflects a documented technical rationale (security margin, performance trade-off, or domestic priority)
B84: A fallback or contingency algorithm is designated for each primary selection
A85: 5.2 Algorithmic Evaluation
B86: Security evaluation has been published for selected algorithms
B87: Published cryptanalysis exists addressing the algorithm's core mathematical hardness assumption
B88: Performance benchmarking has been conducted
A89: 5.3 Protocol & Infrastructure Integration
B90: PQC integration addressed for TLS/HTTPS
B91: PQC integration addressed for VPN/IPsec
B92: PKI migration pathway defined (certificate authorities, certificate issuance)
B93: PQC integration addressed for DNS security (DNSSEC) or equivalent critical protocol
A94: 5.4 Library & Developer Ecosystem
B95: Open-source or publicly available reference implementations exist for domestic standards
B96: PQC libraries are available for major development platforms (Java, Python, C/C++)
B97: Developer documentation or SDK support is publicly accessible

Sheet Results
A1: PQC Evaluation Framework — Results Dashboard
A3: FINAL WEIGHTED SCORES (0 – 100)
B4: =Scoring!C5 -> Nation 1 | C4: =Scoring!D5 -> Nation 2 | D4: =Scoring!E5 -> Nation 3 | E4: =Scoring!F5 -> Nation 4 | F4: Weight
A5: Cat 1: Cryptographic Agility & Migration Readiness | B5: =Scoring!C35 -> 0 | C5: =Scoring!D35 -> 0 | D5: =Scoring!E35 -> 0 | E5: =Scoring!F35 -> 0 | F5: 20%
A6: Cat 2: Governance & Coordination | B6: =Scoring!C64 -> 0 | C6: =Scoring!D64 -> 0 | D6: =Scoring!E64 -> 0 | E6: =Scoring!F64 -> 0 | F6: 25%
A7: Cat 3: Risk & Technical Feasibility | B7: =Scoring!C84 -> 0 | C7: =Scoring!D84 -> 0 | D7: =Scoring!E84 -> 0 | E7: =Scoring!F84 -> 0 | F7: 20%
A8: Cat 4: Standardisation & Compatibility | B8: =Scoring!C101 -> 0 | C8: =Scoring!D101 -> 0 | D8: =Scoring!E101 -> 0 | E8: =Scoring!F101 -> 0 | F8: 15%
A9: Cat 5: Technical | B9: =Scoring!C125 -> 0 | C9: =Scoring!D125 -> 0 | D9: =Scoring!E125 -> 0 | E9: =Scoring!F125 -> 0 | F9: 20%
A11: FINAL SCORE (0 – 100) | B11: =(B5*0.2+B6*0.25+B7*0.2+B8*0.15+B9*0.2)*100 -> 0 | C11: =(C5*0.2+C6*0.25+C7*0.2+C8*0.15+C9*0.2)*100 -> 0 | D11: =(D5*0.2+D6*0.25+D7*0.2+D8*0.15+D9*0.2)*100 -> 0 | E11: =(E5*0.2+E6*0.25+E7*0.2+E8*0.15+E9*0.2)*100 -> 0 | F11: 100%
A14: SUB-FACTOR BREAKDOWN (0.00 – 1.00)
B15: =Scoring!C5 -> Nation 1 | C15: =Scoring!D5 -> Nation 2 | D15: =Scoring!E5 -> Nation 3 | E15: =Scoring!F5 -> Nation 4
A16: Cat 1: Cryptographic Agility & Migration Readiness
A17: 1.1 Inventory & Asset Awareness | B17: =Scoring!C14 -> 0 | C17: =Scoring!D14 -> 0 | D17: =Scoring!E14 -> 0 | E17: =Scoring!F14 -> 0
A18: 1.2 Migration Agility | B18: =Scoring!C19 -> 0 | C18: =Scoring!D19 -> 0 | D18: =Scoring!E19 -> 0 | E18: =Scoring!F19 -> 0
A19: 1.3 Operational Integration | B19: =Scoring!C24 -> 0 | C19: =Scoring!D24 -> 0 | D19: =Scoring!E24 -> 0 | E19: =Scoring!F24 -> 0
A20: 1.4 Hybrid Migration Support | B20: =Scoring!C29 -> 0 | C20: =Scoring!D29 -> 0 | D20: =Scoring!E29 -> 0 | E20: =Scoring!F29 -> 0
A21: 1.5 Supply Chain & Vendor Readiness | B21: =Scoring!C34 -> 0 | C21: =Scoring!D34 -> 0 | D21: =Scoring!E34 -> 0 | E21: =Scoring!F34 -> 0
A22: Cat 2: Governance & Coordination
A23: 2.1 National Strategy | B23: =Scoring!C42 -> 0 | C23: =Scoring!D42 -> 0 | D23: =Scoring!E42 -> 0 | E23: =Scoring!F42 -> 0
A24: 2.2 Coordination | B24: =Scoring!C48 -> 0 | C24: =Scoring!D48 -> 0 | D24: =Scoring!E48 -> 0 | E24: =Scoring!F48 -> 0
A25: 2.3 Regulation | B25: =Scoring!C53 -> 0 | C25: =Scoring!D53 -> 0 | D25: =Scoring!E53 -> 0 | E25: =Scoring!F53 -> 0
A26: 2.4 Workforce | B26: =Scoring!C58 -> 0 | C26: =Scoring!D58 -> 0 | D26: =Scoring!E58 -> 0 | E26: =Scoring!F58 -> 0
A27: 2.5 International Cooperation | B27: =Scoring!C63 -> 0 | C27: =Scoring!D63 -> 0 | D27: =Scoring!E63 -> 0 | E27: =Scoring!F63 -> 0
A28: Cat 3: Risk & Technical Feasibility
A29: 3.1 Quantum Weakness | B29: =Scoring!C71 -> 0 | C29: =Scoring!D71 -> 0 | D29: =Scoring!E71 -> 0 | E29: =Scoring!F71 -> 0
A30: 3.2 Expected Impact | B30: =Scoring!C75 -> 0 | C30: =Scoring!D75 -> 0 | D30: =Scoring!E75 -> 0 | E30: =Scoring!F75 -> 0
A31: 3.3 Estimated Time / Effort / Costs | B31: =Scoring!C79 -> 0 | C31: =Scoring!D79 -> 0 | D31: =Scoring!E79 -> 0 | E31: =Scoring!F79 -> 0
A32: 3.4 Performance & Hardware Readiness | B32: =Scoring!C83 -> 0 | C32: =Scoring!D83 -> 0 | D32: =Scoring!E83 -> 0 | E32: =Scoring!F83 -> 0
A33: Cat 4: Standardisation & Compatibility
A34: 4.1 Interoperability | B34: =Scoring!C91 -> 0 | C34: =Scoring!D91 -> 0 | D34: =Scoring!E91 -> 0 | E34: =Scoring!F91 -> 0
A35: 4.2 Standards Alignment | B35: =Scoring!C95 -> 0 | C35: =Scoring!D95 -> 0 | D35: =Scoring!E95 -> 0 | E35: =Scoring!F95 -> 0
A36: 4.3 Certification & Validation Infrastructure | B36: =Scoring!C100 -> 0 | C36: =Scoring!D100 -> 0 | D36: =Scoring!E100 -> 0 | E36: =Scoring!F100 -> 0
A37: Cat 5: Technical
A38: 5.1 Algorithmic Coverage | B38: =Scoring!C108 -> 0 | C38: =Scoring!D108 -> 0 | D38: =Scoring!E108 -> 0 | E38: =Scoring!F108 -> 0
A39: 5.2 Algorithmic Evaluation | B39: =Scoring!C113 -> 0 | C39: =Scoring!D113 -> 0 | D39: =Scoring!E113 -> 0 | E39: =Scoring!F113 -> 0
A40: 5.3 Protocol & Infrastructure Integration | B40: =Scoring!C119 -> 0 | C40: =Scoring!D119 -> 0 | D40: =Scoring!E119 -> 0 | E40: =Scoring!F119 -> 0
A41: 5.4 Library & Developer Ecosystem | B41: =Scoring!C124 -> 0 | C41: =Scoring!D124 -> 0 | D41: =Scoring!E124 -> 0 | E41: =Scoring!F124 -> 0
